{
  "step_by_step_reasoning": "The architecture shows an automated, single-tenant deployment stack for financial risk reporting. On the left, we have the deployment orchestrator represented by ECS and AMI (with mentions of Terraform, Jenkins, and Ansible). The bottom section contains the core Application Stack with RDS (OLTP database) and Redshift (OLAP data warehouse), which connects to S3 via Redshift Spectrum for warm/historical storage. The top-right shows the security, compliance, and governance block consisting of KMS, Security Hub, GuardDuty, AWS Config, CloudWatch, and CloudTrail, which secure and monitor the application environment and store audit/log data in S3.",
  "graph": {
    "name": "AxiomSL: Risk and Regulatory Reporting Platform on AWS",
    "link": "https://www.youtube.com/watch?v=8TExnSvZqt0",
    "categories": "compute_intensive, data_ingestion",
    "graph_usable": true,
    "notes": "Automated single-tenant SaaS architecture deploying isolated application stacks using ECS, AMI, RDS, and Redshift. Uses Redshift Spectrum to query historical data in S3 and native AWS services for security compliance."
  },
  "nodes": [
    {
      "id": "0",
      "service": "ECS",
      "name": "ECS Orchestrator",
      "notes": "WORKLOAD_PEEK: Handles automated container orchestration as part of the application stack."
    },
    {
      "id": "1",
      "service": "AMI",
      "name": "CIS-Hardened AMIs",
      "notes": "CIS-hardened base machine images used for standardizing deployments."
    },
    {
      "id": "2",
      "service": "RDS",
      "name": "RDS (OLTP)",
      "notes": "DATA_PEEK: Handles transactional relational database workloads."
    },
    {
      "id": "3",
      "service": "RedShift",
      "name": "Redshift (OLAP)",
      "notes": "DATA_PEEK: Used for complex regulatory reporting queries. Leverages RA3 nodes to scale compute and storage independently."
    },
    {
      "id": "4",
      "service": "S3",
      "name": "Amazon S3",
      "notes": "DATA_PEEK: Acts as warm historical storage and secure data lake."
    },
    {
      "id": "5",
      "service": "KMS",
      "name": "KMS Key Management",
      "notes": "Provides key storage and encryption at rest/transit."
    },
    {
      "id": "6",
      "service": "SecurityHub",
      "name": "Security Hub",
      "notes": "Aggregates and prioritizes security alerts and compliance checks."
    },
    {
      "id": "7",
      "service": "GuardDuty",
      "name": "GuardDuty",
      "notes": "Intelligent threat detection monitoring AWS accounts and workloads."
    },
    {
      "id": "8",
      "service": "AWSConfig",
      "name": "AWS Config",
      "notes": "Tracks resource configuration changes and simplifies compliance auditing."
    },
    {
      "id": "9",
      "service": "CloudWatch",
      "name": "CloudWatch",
      "notes": "Monitors resources and applications, generating operational metrics."
    },
    {
      "id": "10",
      "service": "CloudTrail",
      "name": "CloudTrail",
      "notes": "Records and audits all user activity and API calls across the stack."
    }
  ],
  "edges": [
    {
      "source": "0",
      "target": "1",
      "flow_id": 0,
      "seq": "0",
      "type": "data",
      "notes": "Deployments build CIS-hardened AMIs."
    },
    {
      "source": "1",
      "target": "2",
      "flow_id": 0,
      "seq": "1",
      "type": "data",
      "notes": "Deploys transactional application stack instances."
    },
    {
      "source": "1",
      "target": "3",
      "flow_id": 0,
      "seq": "2",
      "type": "data",
      "notes": "Deploys analytical application stack instances."
    },
    {
      "source": "3",
      "target": "4",
      "flow_id": 1,
      "seq": "0",
      "type": "data",
      "notes": "Redshift Spectrum queries warm historical data stored in S3."
    },
    {
      "source": "2",
      "target": "5",
      "flow_id": 2,
      "seq": "0",
      "type": "meta",
      "notes": "Application resources leverage KMS for data encryption."
    },
    {
      "source": "3",
      "target": "5",
      "flow_id": 2,
      "seq": "1",
      "type": "meta",
      "notes": "Redshift clusters use KMS keys for encryption."
    },
    {
      "source": "10",
      "target": "4",
      "flow_id": 2,
      "seq": "2",
      "type": "data",
      "notes": "Audit and operational logs stored securely in S3."
    }
  ]
}