{
  "step_by_step_reasoning": "We identify the main actor as UserConsumerMobile representing the rider and driver apps. Route 53 handles DNS and geolocation routing. ELB distributes traffic to either the legacy Nomad cluster (EC2) or the new EKS cluster. Both compute clusters access dedicated RDS MySQL databases for active data. Cold trip data is eventually archived from the microservices to S3.",
  "graph": {
    "name": "Cabify Mobile Platform Architecture",
    "link": "https://www.youtube.com/watch?v=x76BIV88j_M",
    "categories": "interactive, compute_intensive",
    "graph_usable": true,
    "notes": "Cabify uses this architecture to run real-time ride-sharing and delivery applications, migrating from a Nomad cluster on EC2 to Amazon EKS while utilizing Spot Instances for cost efficiency."
  },
  "nodes": [
    {
      "id": "0",
      "service": "UserConsumerMobile",
      "name": "Mobile Client App",
      "notes": "Mobile apps used by riders and drivers."
    },
    {
      "id": "1",
      "service": "Route 53",
      "name": "Amazon Route 53",
      "notes": "Handles IP geolocation routing during platform migration."
    },
    {
      "id": "2",
      "service": "ELB",
      "name": "Elastic Load Balancing",
      "notes": "Distributes incoming mobile application traffic."
    },
    {
      "id": "3",
      "service": "EC2",
      "name": "Nomad Cluster",
      "notes": "Legacy container orchestration platform running on EC2."
    },
    {
      "id": "4",
      "service": "EKS",
      "name": "Amazon EKS Cluster",
      "notes": "Target Kubernetes cluster running containerized microservices."
    },
    {
      "id": "5",
      "service": "RDS",
      "name": "Amazon RDS MySQL",
      "notes": "Independent databases owned by individual microservices."
    },
    {
      "id": "6",
      "service": "S3",
      "name": "Amazon S3",
      "notes": "Long-term cold storage for completed trip data."
    }
  ],
  "edges": [
    {
      "source": "0",
      "target": "1",
      "flow_id": 1,
      "seq": "1",
      "type": "data",
      "notes": "Resolves domain via Route 53 with geolocation."
    },
    {
      "source": "0",
      "target": "2",
      "flow_id": 2,
      "seq": "2",
      "type": "data",
      "notes": "Sends application traffic to load balancers."
    },
    {
      "source": "2",
      "target": "3",
      "flow_id": 3,
      "seq": "3a",
      "type": "data",
      "notes": "Routes traffic to Nomad container services."
    },
    {
      "source": "2",
      "target": "4",
      "flow_id": 3,
      "seq": "3b",
      "type": "data",
      "notes": "Routes traffic to migrated EKS services."
    },
    {
      "source": "3",
      "target": "4",
      "flow_id": 4,
      "seq": "4",
      "type": "data",
      "notes": "Facilitates migration/routing between clusters."
    },
    {
      "source": "3",
      "target": "5",
      "flow_id": 5,
      "seq": "5a",
      "type": "data",
      "notes": "Writes and reads active service data."
    },
    {
      "source": "4",
      "target": "5",
      "flow_id": 5,
      "seq": "5b",
      "type": "data",
      "notes": "Writes and reads active service data."
    },
    {
      "source": "4",
      "target": "6",
      "flow_id": 6,
      "seq": "6",
      "type": "data",
      "notes": "Archives cold data for long-term storage."
    }
  ]
}